COPYING.txt
MANIFEST.in
PROFILING.txt
README.rst
TODO.txt
setup.py
friture/__init__.py
friture/about.py
friture/analyzer.py
friture/audiobackend.py
friture/audiobuffer.py
friture/audioproc.py
friture/controlbar.py
friture/defaults.py
friture/delay_estimator.py
friture/dock.py
friture/dockmanager.py
friture/exceptionhandler.py
friture/filter.py
friture/filter_design.py
friture/friture_rc.py
friture/generated_filters.py
friture/generator.py
friture/histplot.py
friture/imageplot.py
friture/levels.py
friture/levels_settings.py
friture/longlevels.py
friture/longlevels_settings.py
friture/octavespectrum.py
friture/octavespectrum_settings.py
friture/qsynthmeter.py
friture/renard.py
friture/ringbuffer.py
friture/scope.py
friture/settings.py
friture/spectrogram.py
friture/spectrogram_image.py
friture/spectrogram_settings.py
friture/spectrum.py
friture/spectrumPlotWidget.py
friture/spectrum_settings.py
friture/statisticswidget.py
friture/tilelayout.py
friture/timeplot.py
friture/ui_friture.py
friture/ui_settings.py
friture/widgetdict.py
friture.egg-info/PKG-INFO
friture.egg-info/SOURCES.txt
friture.egg-info/dependency_links.txt
friture.egg-info/requires.txt
friture.egg-info/top_level.txt
friture/generators/__init__.py
friture/generators/burst.py
friture/generators/pink.py
friture/generators/sine.py
friture/generators/sweep.py
friture/generators/white.py
friture/plotting/__init__.py
friture/plotting/canvasBackground.py
friture/plotting/canvasWidget.py
friture/plotting/cmrmap_generate.py
friture/plotting/coordinateTransform.py
friture/plotting/generated_cmrmap.py
friture/plotting/glCanvasWidget.py
friture/plotting/grid.py
friture/plotting/legendWidget.py
friture/plotting/quadsItem.py
friture/plotting/scaleBar.py
friture/plotting/scaleDivision.py
friture/plotting/scaleWidget.py
friture/plotting/titleWidget.py
friture/signal/__init__.py
friture/signal/correlation.py
friture/signal/decimate.py
friture/signal/frequency_resampler.py
friture/signal/online_linear_2D_resampler.py
friture/signal/scipy_resample.py
friture_extensions/__init__.py
friture_extensions/exp_smoothing_conv.c
friture_extensions/exp_smoothing_conv.pyx
