Metadata-Version: 1.1
Name: friture
Version: 0.38
Summary: Real-time visualization of live audio data
Home-page: http://www.friture.org
Author: Timothée Lecomte
Author-email: contact@friture.org
License: GNU GENERAL PUBLIC LICENSE
Keywords: audio,spectrum,spectrogram
Platform: UNKNOWN
Classifier: Programming Language :: Python
Classifier: Programming Language :: Cython
Classifier: Development Status :: 4 - Beta
Classifier: Environment :: MacOS X
Classifier: Environment :: Win32 (MS Windows)
Classifier: Environment :: X11 Applications :: Qt
Classifier: Intended Audience :: End Users/Desktop
Classifier: License :: OSI Approved :: GNU General Public License (GPL)
Classifier: Operating System :: OS Independent
Classifier: Topic :: Multimedia :: Sound/Audio :: Analysis
Classifier: Topic :: Multimedia :: Sound/Audio :: Speech
